LICENSE
MANIFEST.in
README.md
setup.py
AbundanceMatching/__init__.py
AbundanceMatching/abundance_function.py
AbundanceMatching/fiducial_deconv_wrapper.py
AbundanceMatching/fiducial_deconvolute.c
AbundanceMatching/halo_abundance_function.py
AbundanceMatching/version.py
AbundanceMatching.egg-info/PKG-INFO
AbundanceMatching.egg-info/SOURCES.txt
AbundanceMatching.egg-info/dependency_links.txt
AbundanceMatching.egg-info/requires.txt
AbundanceMatching.egg-info/top_level.txt